odoo/addons/sale_order_invoice_shipping_partner_restrict/LICENSE
odoo/addons/sale_order_invoice_shipping_partner_restrict/README.rst
odoo/addons/sale_order_invoice_shipping_partner_restrict/__init__.py
odoo/addons/sale_order_invoice_shipping_partner_restrict/__manifest__.py
odoo/addons/sale_order_invoice_shipping_partner_restrict/images/screen.png
odoo/addons/sale_order_invoice_shipping_partner_restrict/models/__init__.py
odoo/addons/sale_order_invoice_shipping_partner_restrict/models/sale_order.py
odoo/addons/sale_order_invoice_shipping_partner_restrict/static/description/icon.png
odoo/addons/sale_order_invoice_shipping_partner_restrict/static/description/index.html
odoo_addon_sale_order_invoice_shipping_partner_restrict-16.0.1.0.0.dist-info/METADATA
odoo_addon_sale_order_invoice_shipping_partner_restrict-16.0.1.0.0.dist-info/WHEEL
odoo_addon_sale_order_invoice_shipping_partner_restrict-16.0.1.0.0.dist-info/top_level.txt
odoo_addon_sale_order_invoice_shipping_partner_restrict-16.0.1.0.0.dist-info/RECORD
